baicai_tutor/__init__.py
baicai_tutor/agents/graphs/nodes/__init__.py
baicai_tutor/agents/graphs/nodes/analyst_node.py
baicai_tutor/agents/graphs/nodes/questioner_node.py
baicai_tutor/agents/graphs/nodes/students_node.py
baicai_tutor/agents/graphs/nodes/surveyor_node.py
baicai_tutor/agents/graphs/nodes/user_node.py
baicai_tutor/agents/graphs/state.py
baicai_tutor/agents/graphs/tutor_builder.py
baicai_tutor/agents/roles/__init__.py
baicai_tutor/agents/roles/concept_explainer.py
baicai_tutor/agents/roles/hinter.py
baicai_tutor/agents/roles/questioner.py
baicai_tutor/agents/roles/student.py
baicai_tutor/agents/roles/surveyor.py
baicai_tutor/agents/roles/text_rewriter.py
baicai_tutor/utils/__init__.py
baicai_tutor/utils/irt.py
baicai_tutor/utils/md_process.py
baicai_tutor/utils/setups.py
baicai_tutor-0.1.0.dist-info/METADATA
baicai_tutor-0.1.0.dist-info/WHEEL
baicai_tutor-0.1.0.dist-info/entry_points.txt
baicai_tutor-0.1.0.dist-info/RECORD
