Metadata-Version: 2.3
Name: baicai-tutor
Version: 0.1.0
Summary: AI tutor for Everyone
License: MIT
Keywords: python,agent,AI,machine learning,LLM
Author: Zhaoyang tech
Author-email: gengyabc@aliyun.com
Requires-Python: >=3.10,<3.12
Classifier: License :: OSI Approved :: MIT License
Classifier: Programming Language :: Python :: 3
Classifier: Programming Language :: Python :: 3.10
Classifier: Programming Language :: Python :: 3.11
Requires-Dist: baicai-base (==0.1.2)
Requires-Dist: girth (>=0.8.0,<0.9.0)
